dublindistance/__init__.py
dublindistance/calculations.py
dublindistance/transport_suggestions.py
dublindistance-0.1.7.dist-info/METADATA
dublindistance-0.1.7.dist-info/WHEEL
dublindistance-0.1.7.dist-info/top_level.txt
dublindistance-0.1.7.dist-info/RECORD
