Metadata-Version: 2.4
Name: dublindistance
Version: 0.1.7
Summary: Simple Dublin area distance and transport suggestion tool
Author: Jeevanjot Singh
License: MIT
Requires-Dist: geopy
Dynamic: author
Dynamic: license
Dynamic: requires-dist
Dynamic: summary
